{
    "form": {
        "layout": "horizontal",
        "labelAlign": "left",
        "style": {
            "padding": "10px 24px"
        },
        "colon": false
    },
    "schema": {
        "type": "object",
        "properties": {
            "tableLayout": {
                "type": "void",
                "x-component": "FormLayout",
                "x-component-props": {
                    "style": {
                        "borderRadius": "6px",
                        "boxShadow": "0 2px 8px rgba(0,0,0,0.1)",
                        "padding": "16px",
                        "backgroundColor": "#fff"
                    }
                },
                "name": "tableLayout",
                "x-designable-id": "qmkqbw6gqt1",
                "properties": {
                    "tableHeader": {
                        "type": "string",
                        "x-component": "Text",
                        "x-component-props": {
                            "content": "项目现场踏勘记录表",
                            "mode": "h1",
                            "style": {
                                "display": "block",
                                "fontFamily": "arial black,sans-serif",
                                "margin": "10px 0 20px 0",
                                "textAlign": "center"
                            }
                        },
                        "name": "tableHeader",
                        "x-designable-id": "jq7wb4loprc",
                        "x-index": 0
                    },
                    "applicantInfoGrid": {
                        "type": "void",
                        "x-component": "FormGrid",
                        "x-component-props": {
                            "maxColumns": 3,
                            "style": {
                                "margin": "10px 0"
                            }
                        },
                        "name": "applicantInfoGrid",
                        "x-designable-id": "applicant_info_grid",
                        "x-index": 1,
                        "properties": {
                            "applicantId": {
                                "type": "string",
                                "title": "申请人",
                                "x-decorator": "FormItem",
                                "x-component": "Select",
                                "x-dynamic-data": {
                                    "type": "user"
                                },
                                "x-component-props": {
                                    "placeholder": "请选择申请人",
                                    "showSearch": true
                                },
                                "name": "applicantId",
                                "x-designable-id": "applicant_id_field",
                                "x-index": 0
                            },
                            "deptId": {
                                "type": "string",
                                "title": "所属部门",
                                "x-decorator": "FormItem",
                                "x-component": "Select",
                                "x-dynamic-data": {
                                    "type": "dept"
                                },
                                "x-component-props": {
                                    "placeholder": "请选择部门",
                                    "showSearch": true
                                },
                                "name": "deptId",
                                "x-designable-id": "dept_id_field",
                                "x-index": 1
                            },
                            "applyTime": {
                                "type": "string",
                                "title": "申请时间",
                                "x-decorator": "FormItem",
                                "x-component": "DatePicker",
                                "x-component-props": {
                                    "readOnly": true
                                },
                                "name": "applyTime",
                                "x-designable-id": "apply_time_field",
                                "x-index": 2
                            }
                        }
                    },
                    "basicInfoSection": {
                        "type": "void",
                        "x-component": "Card",
                        "x-component-props": {
                            "title": "项目基本信息",
                            "size": "small",
                            "styles": {
                                "header": {
                                    "textAlign": "center",
                                    "backgroundColor": "rgb(200, 221, 252)",
                                    "fontSize": "16px",
                                    "fontWeight": "bold"
                                }
                            }
                        },
                        "name": "basicInfoSection",
                        "x-designable-id": "asjl55u5k2w",
                        "properties": {
                            "basicInfoGrid": {
                                "type": "void",
                                "x-component": "FormGrid",
                                "x-component-props": {
                                    "maxColumns": 4,
                                    "columnGap": 10
                                },
                                "name": "basicInfoGrid",
                                "x-designable-id": "ktny70g4f7p",
                                "properties": {
                                    "projectId": {
                                        "type": "string",
                                        "title": "项目名称",
                                        "x-decorator": "FormItem",
                                        "x-decorator-props": {
                                            "gridSpan": 4
                                        },
                                        "x-component": "Select",
                                        "x-dynamic-data": {
                                            "type": "project"
                                        },
                                        "x-component-props": {
                                            "placeholder": "请选择项目",
                                            "showSearch": true,
                                            "filterOption": true,
                                            "optionFilterProp": "label"
                                        },
                                        "x-validator": [
                                            {
                                                "required": true,
                                                "message": "请选择项目"
                                            }
                                        ],
                                        "name": "projectId",
                                        "x-index": 0,
                                        "x-reactions": [
                                            {
                                                "dependencies": [],
                                                "fulfill": {
                                                    "run": "\n                if (!$self.value) return;\n                const projectId = $self.value;\n                $form.$http.get('/api/v1/forms/data/project/' + projectId)\n                  .then(res => {\n                    const data = res.data || {};\n                    $form.setFieldState('projectNumber', state => { state.value = data.projectNumber || ''; });\n                    $form.setFieldState('projectManagerId', state => { state.value = data.projectManagerId ? String(data.projectManagerId) : ''; });\n                    $form.setFieldState('responsibleDeptId', state => { state.value = data.responsibleDeptId ? String(data.responsibleDeptId) : ''; });\n                    $form.setFieldState('projectLevelKey', state => { state.value = data.projectLevelKey || ''; });\n                    $form.setFieldState('controlLevelKey', state => { state.value = data.controlLevelKey || ''; });\n                    $form.setFieldState('projectAuditorId', state => { state.value = data.projectAuditorId ? String(data.projectAuditorId) : ''; });\n                  })\n                  .catch(err => { console.error('加载项目详情失败:', err); });\n              "
                                                }
                                            }
                                        ],
                                        "x-designable-id": "8me6fg82bj5"
                                    },
                                    "projectNumber": {
                                        "type": "string",
                                        "title": "项目编号",
                                        "x-decorator": "FormItem",
                                        "x-decorator-props": {
                                            "gridSpan": 1
                                        },
                                        "x-component": "Input",
                                        "name": "projectNumber",
                                        "x-component-props": {},
                                        "x-pattern": "readPretty",
                                        "x-designable-id": "cjjcx61t69y",
                                        "x-validator": [],
                                        "x-index": 1
                                    },
                                    "projectManagerId": {
                                        "type": "string",
                                        "title": "项目负责人",
                                        "x-decorator": "FormItem",
                                        "x-component": "Select",
                                        "x-dynamic-data": {
                                            "type": "user"
                                        },
                                        "name": "projectManagerId",
                                        "x-component-props": {},
                                        "x-pattern": "readPretty",
                                        "x-designable-id": "fpi9isik6we",
                                        "x-index": 2
                                    },
                                    "responsibleDeptId": {
                                        "type": "string",
                                        "title": "承担部门",
                                        "x-decorator": "FormItem",
                                        "x-component": "Select",
                                        "x-dynamic-data": {
                                            "type": "dept"
                                        },
                                        "name": "responsibleDeptId",
                                        "x-component-props": {},
                                        "x-pattern": "readPretty",
                                        "x-designable-id": "t04t67rto2p",
                                        "x-index": 3
                                    },
                                    "controlLevelKey": {
                                        "type": "string",
                                        "title": "流程管控强度",
                                        "x-decorator": "FormItem",
                                        "x-component": "Select",
                                        "x-dynamic-data": {
                                            "type": "dict",
                                            "dictKey": "control_level"
                                        },
                                        "name": "controlLevelKey",
                                        "x-component-props": {},
                                        "x-pattern": "readPretty",
                                        "x-designable-id": "p153ulzowgf",
                                        "x-index": 4
                                    },
                                    "projectLevelKey": {
                                        "type": "string",
                                        "title": "项目分级",
                                        "x-decorator": "FormItem",
                                        "x-component": "Select",
                                        "x-dynamic-data": {
                                            "type": "dict",
                                            "dictKey": "project_level"
                                        },
                                        "name": "projectLevelKey",
                                        "x-component-props": {},
                                        "x-pattern": "readPretty",
                                        "x-designable-id": "n7dvn1244wn",
                                        "x-index": 5
                                    },
                                    "projectAuditorId": {
                                        "type": "string",
                                        "title": "项目审核",
                                        "x-decorator": "FormItem",
                                        "x-component": "Select",
                                        "x-dynamic-data": {
                                            "type": "user"
                                        },
                                        "name": "projectAuditorId",
                                        "x-component-props": {},
                                        "x-pattern": "readPretty",
                                        "x-designable-id": "9mtedezyabe",
                                        "x-index": 6
                                    }
                                },
                                "x-index": 0
                            }
                        },
                        "x-index": 2
                    },
                    "internalJudgmentSection": {
                        "type": "void",
                        "x-component": "Card",
                        "x-component-props": {
                            "title": "所内自主判断(仅适用于IV、V类流程)",
                            "size": "small",
                            "styles": {
                                "header": {
                                    "textAlign": "center",
                                    "backgroundColor": "rgb(200, 221, 252)",
                                    "fontSize": "16px",
                                    "fontWeight": "bold"
                                }
                            },
                            "style": {
                                "marginTop": "16px"
                            }
                        },
                        "name": "internalJudgmentSection",
                        "x-designable-id": "9ox5f4plckx",
                        "properties": {
                            "judgmentGrid": {
                                "type": "void",
                                "x-component": "FormGrid",
                                "x-component-props": {
                                    "maxColumns": 2,
                                    "columnGap": 10
                                },
                                "name": "judgmentGrid",
                                "x-designable-id": "ddomi5urt7h",
                                "properties": {
                                    "isSkipStage": {
                                        "type": "string",
                                        "title": "是否跳过此阶段",
                                        "x-decorator": "FormItem",
                                        "x-component": "Radio.Group",
                                        "x-component-props": {
                                            "options": [
                                                {
                                                    "label": "是",
                                                    "value": "yes"
                                                },
                                                {
                                                    "label": "否",
                                                    "value": "no"
                                                }
                                            ]
                                        },
                                        "name": "isSkipStage",
                                        "default": "no",
                                        "x-designable-id": "7dfbyp2nu42",
                                        "x-index": 0
                                    },
                                    "emptyCol": {
                                        "type": "void",
                                        "x-component": "FormGrid.GridColumn",
                                        "name": "emptyCol",
                                        "x-designable-id": "cvvvh3levd6",
                                        "x-index": 1
                                    },
                                    "skipReason": {
                                        "type": "string",
                                        "title": "跳过原因",
                                        "x-decorator": "FormItem",
                                        "x-decorator-props": {
                                            "gridSpan": 2
                                        },
                                        "x-component": "Input.TextArea",
                                        "name": "skipReason",
                                        "x-reactions": {
                                            "dependencies": [
                                                "isSkipStage"
                                            ],
                                            "fulfill": {
                                                "state": {
                                                    "visible": "{{$deps[0] === 'yes'}}"
                                                }
                                            }
                                        },
                                        "x-designable-id": "ovjbufjs7s6",
                                        "x-index": 2
                                    },
                                    "leaderApprovalId": {
                                        "type": "string",
                                        "title": "领导审批",
                                        "x-decorator": "FormItem",
                                        "x-decorator-props": {
                                            "gridSpan": 2
                                        },
                                        "x-component": "Input.TextArea",
                                        "x-component-props": {
                                            "rows": 4,
                                            "placeholder": "由(项目主管/所长)填写"
                                        },
                                        "name": "leaderApprovalId",
                                        "x-reactions": {
                                            "dependencies": [
                                                "isSkipStage"
                                            ],
                                            "fulfill": {
                                                "state": {
                                                    "visible": "{{$deps[0] === 'yes'}}"
                                                }
                                            }
                                        },
                                        "x-designable-id": "ue2rni1d15x",
                                        "x-index": 3
                                    }
                                },
                                "x-index": 0
                            }
                        },
                        "x-index": 3
                    },
                    "surveyInfoSection": {
                        "type": "void",
                        "x-component": "Card",
                        "x-component-props": {
                            "title": "踏勘信息",
                            "size": "small",
                            "styles": {
                                "header": {
                                    "textAlign": "center",
                                    "backgroundColor": "rgb(200, 221, 252)",
                                    "fontSize": "16px",
                                    "fontWeight": "bold"
                                }
                            },
                            "style": {
                                "marginTop": "16px"
                            }
                        },
                        "name": "surveyInfoSection",
                        "x-designable-id": "qtremgvs581",
                        "properties": {
                            "surveyInfoGrid": {
                                "type": "void",
                                "x-component": "FormGrid",
                                "x-component-props": {
                                    "maxColumns": 2,
                                    "columnGap": 10
                                },
                                "name": "surveyInfoGrid",
                                "x-designable-id": "ob4hktvwfp9",
                                "properties": {
                                    "surveyLocation": {
                                        "type": "string",
                                        "title": "踏勘地点",
                                        "x-decorator": "FormItem",
                                        "x-component": "Input",
                                        "name": "surveyLocation",
                                        "x-designable-id": "b7f13wwzbo8",
                                        "x-index": 0
                                    },
                                    "surveyDate": {
                                        "type": "string",
                                        "title": "踏勘日期",
                                        "x-decorator": "FormItem",
                                        "x-component": "DatePicker",
                                        "name": "surveyDate",
                                        "x-designable-id": "d42rtk1y35k",
                                        "x-index": 1
                                    },
                                    "isPmOnSite": {
                                        "type": "string",
                                        "title": "项目负责人是否到场",
                                        "x-decorator": "FormItem",
                                        "x-component": "Radio.Group",
                                        "x-component-props": {
                                            "options": [
                                                {
                                                    "label": "是",
                                                    "value": "yes"
                                                },
                                                {
                                                    "label": "否",
                                                    "value": "no"
                                                }
                                            ]
                                        },
                                        "name": "isPmOnSite",
                                        "x-designable-id": "sls40qdomrs",
                                        "x-index": 2
                                    },
                                    "surveyCount": {
                                        "type": "number",
                                        "title": "已踏勘次数",
                                        "x-decorator": "FormItem",
                                        "x-component": "NumberPicker",
                                        "name": "surveyCount",
                                        "x-designable-id": "bdgmhkrav2i",
                                        "x-index": 3
                                    },
                                    "participants": {
                                        "type": "array",
                                        "title": "参与踏勘成员",
                                        "x-decorator": "FormItem",
                                        "x-decorator-props": {
                                            "gridSpan": 2
                                        },
                                        "x-component": "Select",
                                        "x-component-props": {
                                            "mode": "multiple",
                                            "placeholder": "请选择参与人员"
                                        },
                                        "x-dynamic-data": {
                                            "type": "user"
                                        },
                                        "name": "participants",
                                        "x-designable-id": "q9tu78jei7p",
                                        "x-index": 4
                                    }
                                },
                                "x-index": 0
                            }
                        },
                        "x-index": 4
                    },
                    "surveyDetailCard": {
                        "type": "void",
                        "x-component": "Card",
                        "x-component-props": {
                            "title": "规划范围内踏勘纪录",
                            "size": "small",
                            "styles": {
                                "header": {
                                    "textAlign": "center",
                                    "backgroundColor": "rgb(200, 221, 252)",
                                    "fontSize": "16px",
                                    "fontWeight": "bold",
                                    "border": "1px solid #d9d9d9",
                                    "borderBottom": "none"
                                },
                                "body": {
                                    "padding": 0
                                }
                            },
                            "style": {
                                "marginTop": "16px"
                            }
                        },
                        "name": "surveyDetailCard",
                        "x-designable-id": "c39w7jvzzli",
                        "properties": {
                            "tableContainer": {
                                "type": "void",
                                "x-component": "div",
                                "x-component-props": {
                                    "style": {
                                        "border": "1px solid #d9d9d9",
                                        "borderRight": "none",
                                        "borderBottom": "none"
                                    }
                                },
                                "name": "tableContainer",
                                "x-designable-id": "p5yg55s07lx",
                                "properties": {
                                    "headerRow": {
                                        "type": "void",
                                        "x-component": "FormGrid",
                                        "x-component-props": {
                                            "maxColumns": 10,
                                            "style": {
                                                "backgroundColor": "#f5f5f5"
                                            }
                                        },
                                        "name": "headerRow",
                                        "x-designable-id": "wdi481bl5ew",
                                        "properties": {
                                            "col1": {
                                                "type": "void",
                                                "x-component": "Text",
                                                "x-component-props": {
                                                    "content": "踏勘分类",
                                                    "style": {
                                                        "fontWeight": "bold",
                                                        "textAlign": "center",
                                                        "display": "flex",
                                                        "alignItems": "center",
                                                        "justifyContent": "center",
                                                        "height": "40px",
                                                        "borderRight": "1px solid #d9d9d9",
                                                        "borderBottom": "1px solid #d9d9d9"
                                                    }
                                                },
                                                "x-decorator-props": {
                                                    "gridSpan": 2
                                                },
                                                "name": "col1",
                                                "x-decorator": "FormGrid.GridColumn",
                                                "x-designable-id": "t853970ty41",
                                                "x-index": 0
                                            },
                                            "col2": {
                                                "type": "void",
                                                "x-component": "Text",
                                                "x-component-props": {
                                                    "content": "踏勘详细内容",
                                                    "style": {
                                                        "fontWeight": "bold",
                                                        "textAlign": "center",
                                                        "display": "flex",
                                                        "alignItems": "center",
                                                        "justifyContent": "center",
                                                        "height": "40px",
                                                        "borderRight": "1px solid #d9d9d9",
                                                        "borderBottom": "1px solid #d9d9d9"
                                                    }
                                                },
                                                "x-decorator-props": {
                                                    "gridSpan": 6
                                                },
                                                "name": "col2",
                                                "x-decorator": "FormGrid.GridColumn",
                                                "x-designable-id": "mkafof4ydnt",
                                                "x-index": 1
                                            },
                                            "col3": {
                                                "type": "void",
                                                "x-component": "Text",
                                                "x-component-props": {
                                                    "content": "核实情况",
                                                    "style": {
                                                        "fontWeight": "bold",
                                                        "textAlign": "center",
                                                        "display": "flex",
                                                        "alignItems": "center",
                                                        "justifyContent": "center",
                                                        "height": "40px",
                                                        "borderRight": "1px solid #d9d9d9",
                                                        "borderBottom": "1px solid #d9d9d9"
                                                    }
                                                },
                                                "x-decorator-props": {
                                                    "gridSpan": 2
                                                },
                                                "name": "col3",
                                                "x-decorator": "FormGrid.GridColumn",
                                                "x-designable-id": "oe4x6k6a2je",
                                                "x-index": 2
                                            }
                                        },
                                        "x-index": 0
                                    },
                                    "row1": {
                                        "type": "void",
                                        "x-component": "FormGrid",
                                        "x-component-props": {
                                            "maxColumns": 10
                                        },
                                        "name": "row1",
                                        "x-designable-id": "h4y3n4mq3tg",
                                        "properties": {
                                            "catName": {
                                                "type": "void",
                                                "x-component": "Text",
                                                "x-component-props": {
                                                    "content": "1.地形图检查",
                                                    "style": {
                                                        "display": "flex",
                                                        "alignItems": "center",
                                                        "justifyContent": "center",
                                                        "height": "100%",
                                                        "fontWeight": "bold",
                                                        "borderRight": "1px solid #d9d9d9",
                                                        "borderBottom": "1px solid #d9d9d9",
                                                        "padding": "10px"
                                                    }
                                                },
                                                "x-decorator-props": {
                                                    "gridSpan": 2
                                                },
                                                "name": "catName",
                                                "x-decorator": "FormGrid.GridColumn",
                                                "x-designable-id": "m2hbkiqj3gg",
                                                "x-index": 0
                                            },
                                            "catContent": {
                                                "type": "void",
                                                "x-component": "Text",
                                                "x-component-props": {
                                                    "content": "(1) 地形地貌、地形走向、河流、明暗渠等\n(2) 地上建、构筑物 (位置、形状、层数、名称、功能、权属等)\n(3) 市政管线和市政设施 (如电力架空线路、水厂、电厂、污水厂、加油站、公交场站、变电站等)\n(4) 地上文物、古树名木",
                                                    "style": {
                                                        "whiteSpace": "pre-wrap",
                                                        "padding": "10px",
                                                        "lineHeight": "1.8",
                                                        "borderRight": "1px solid #d9d9d9",
                                                        "borderBottom": "1px solid #d9d9d9"
                                                    }
                                                },
                                                "x-decorator-props": {
                                                    "gridSpan": 6
                                                },
                                                "name": "catContent",
                                                "x-decorator": "FormGrid.GridColumn",
                                                "x-designable-id": "gf2zzgboexr",
                                                "x-index": 1
                                            },
                                            "statusCell": {
                                                "type": "void",
                                                "x-component": "div",
                                                "x-component-props": {
                                                    "style": {
                                                        "display": "flex",
                                                        "alignItems": "center",
                                                        "justifyContent": "center",
                                                        "height": "100%",
                                                        "borderRight": "1px solid #d9d9d9",
                                                        "borderBottom": "1px solid #d9d9d9"
                                                    }
                                                },
                                                "x-decorator-props": {
                                                    "gridSpan": 2
                                                },
                                                "name": "statusCell",
                                                "x-decorator": "FormGrid.GridColumn",
                                                "x-designable-id": "ufd5oxgv9y8",
                                                "properties": {
                                                    "topographicCheckStatus": {
                                                        "type": "string",
                                                        "x-decorator": "FormItem",
                                                        "x-component": "Radio.Group",
                                                        "x-component-props": {
                                                            "options": [
                                                                {
                                                                    "label": "已核实",
                                                                    "value": "verified"
                                                                },
                                                                {
                                                                    "label": "未核实",
                                                                    "value": "unverified"
                                                                }
                                                            ]
                                                        },
                                                        "name": "topographicCheckStatus",
                                                        "x-decorator-props": {
                                                            "style": {
                                                                "marginBottom": "0px"
                                                            }
                                                        },
                                                        "x-designable-id": "8bcjue1jint",
                                                        "x-index": 0
                                                    }
                                                },
                                                "x-index": 2
                                            }
                                        },
                                        "x-index": 1
                                    },
                                    "row2": {
                                        "type": "void",
                                        "x-component": "FormGrid",
                                        "x-component-props": {
                                            "maxColumns": 10
                                        },
                                        "name": "row2",
                                        "x-designable-id": "eycthe2wtpw",
                                        "properties": {
                                            "catName": {
                                                "type": "void",
                                                "x-component": "Text",
                                                "x-component-props": {
                                                    "content": "2.建设项目核实",
                                                    "style": {
                                                        "display": "flex",
                                                        "alignItems": "center",
                                                        "justifyContent": "center",
                                                        "height": "100%",
                                                        "fontWeight": "bold",
                                                        "borderRight": "1px solid #d9d9d9",
                                                        "borderBottom": "1px solid #d9d9d9",
                                                        "padding": "10px"
                                                    }
                                                },
                                                "x-decorator-props": {
                                                    "gridSpan": 2
                                                },
                                                "name": "catName",
                                                "x-decorator": "FormGrid.GridColumn",
                                                "x-designable-id": "ozxujyn0moh",
                                                "x-index": 0
                                            },
                                            "catContent": {
                                                "type": "void",
                                                "x-component": "Text",
                                                "x-component-props": {
                                                    "content": "(5) 用地信息 (如土地权属、边界等)\n(6) 已建未批 (如权属、边界、性质等)\n(7) 已批未建 (如权属、边界、发证日期、性质等)\n(8) 已批在建 (如权属、边界、发证日期、性质等)",
                                                    "style": {
                                                        "whiteSpace": "pre-wrap",
                                                        "padding": "10px",
                                                        "lineHeight": "1.8",
                                                        "borderRight": "1px solid #d9d9d9",
                                                        "borderBottom": "1px solid #d9d9d9"
                                                    }
                                                },
                                                "x-decorator-props": {
                                                    "gridSpan": 6
                                                },
                                                "name": "catContent",
                                                "x-decorator": "FormGrid.GridColumn",
                                                "x-designable-id": "3u8x836ymez",
                                                "x-index": 1
                                            },
                                            "statusCell": {
                                                "type": "void",
                                                "x-component": "div",
                                                "x-component-props": {
                                                    "style": {
                                                        "display": "flex",
                                                        "alignItems": "center",
                                                        "justifyContent": "center",
                                                        "height": "100%",
                                                        "borderRight": "1px solid #d9d9d9",
                                                        "borderBottom": "1px solid #d9d9d9"
                                                    }
                                                },
                                                "x-decorator-props": {
                                                    "gridSpan": 2
                                                },
                                                "name": "statusCell",
                                                "x-decorator": "FormGrid.GridColumn",
                                                "x-designable-id": "4e7qkgxkgjk",
                                                "properties": {
                                                    "constructionCheckStatus": {
                                                        "type": "string",
                                                        "x-decorator": "FormItem",
                                                        "x-component": "Radio.Group",
                                                        "x-component-props": {
                                                            "options": [
                                                                {
                                                                    "label": "已核实",
                                                                    "value": "verified"
                                                                },
                                                                {
                                                                    "label": "未核实",
                                                                    "value": "unverified"
                                                                }
                                                            ]
                                                        },
                                                        "name": "constructionCheckStatus",
                                                        "x-decorator-props": {
                                                            "style": {
                                                                "marginBottom": "0px"
                                                            }
                                                        },
                                                        "x-designable-id": "k0ge10z85ci",
                                                        "x-index": 0
                                                    }
                                                },
                                                "x-index": 2
                                            }
                                        },
                                        "x-index": 2
                                    },
                                    "row3": {
                                        "type": "void",
                                        "x-component": "FormGrid",
                                        "x-component-props": {
                                            "maxColumns": 10
                                        },
                                        "name": "row3",
                                        "x-designable-id": "pm7whi9b1g3",
                                        "properties": {
                                            "catName": {
                                                "type": "void",
                                                "x-component": "Text",
                                                "x-component-props": {
                                                    "content": "3.地下设施核实",
                                                    "style": {
                                                        "display": "flex",
                                                        "alignItems": "center",
                                                        "justifyContent": "center",
                                                        "height": "100%",
                                                        "fontWeight": "bold",
                                                        "borderRight": "1px solid #d9d9d9",
                                                        "borderBottom": "1px solid #d9d9d9",
                                                        "padding": "10px"
                                                    }
                                                },
                                                "x-decorator-props": {
                                                    "gridSpan": 2
                                                },
                                                "name": "catName",
                                                "x-decorator": "FormGrid.GridColumn",
                                                "x-designable-id": "161dvr7bz81",
                                                "x-index": 0
                                            },
                                            "catContent": {
                                                "type": "void",
                                                "x-component": "Text",
                                                "x-component-props": {
                                                    "content": "(9) 核实已建道路下敷设各类管线 (水雨污气电讯、照明等) 标识情况\n(10) 核实用地内地下市政干管和重大地下设施 (燃气、电力、电信、输水、输油/人防、地铁等) 标识情况\n(11) 核实地下文物标识情况",
                                                    "style": {
                                                        "whiteSpace": "pre-wrap",
                                                        "padding": "10px",
                                                        "lineHeight": "1.8",
                                                        "borderRight": "1px solid #d9d9d9",
                                                        "borderBottom": "1px solid #d9d9d9"
                                                    }
                                                },
                                                "x-decorator-props": {
                                                    "gridSpan": 6
                                                },
                                                "name": "catContent",
                                                "x-decorator": "FormGrid.GridColumn",
                                                "x-designable-id": "z76j54kpemz",
                                                "x-index": 1
                                            },
                                            "statusCell": {
                                                "type": "void",
                                                "x-component": "div",
                                                "x-component-props": {
                                                    "style": {
                                                        "display": "flex",
                                                        "alignItems": "center",
                                                        "justifyContent": "center",
                                                        "height": "100%",
                                                        "borderRight": "1px solid #d9d9d9",
                                                        "borderBottom": "1px solid #d9d9d9"
                                                    }
                                                },
                                                "x-decorator-props": {
                                                    "gridSpan": 2
                                                },
                                                "name": "statusCell",
                                                "x-decorator": "FormGrid.GridColumn",
                                                "x-designable-id": "7363nls2d0m",
                                                "properties": {
                                                    "undergroundCheckStatus": {
                                                        "type": "string",
                                                        "x-decorator": "FormItem",
                                                        "x-component": "Radio.Group",
                                                        "x-component-props": {
                                                            "options": [
                                                                {
                                                                    "label": "已核实",
                                                                    "value": "verified"
                                                                },
                                                                {
                                                                    "label": "未核实",
                                                                    "value": "unverified"
                                                                }
                                                            ]
                                                        },
                                                        "name": "undergroundCheckStatus",
                                                        "x-decorator-props": {
                                                            "style": {
                                                                "marginBottom": "0px"
                                                            }
                                                        },
                                                        "x-designable-id": "o6lvi2wqzto",
                                                        "x-index": 0
                                                    }
                                                },
                                                "x-index": 2
                                            }
                                        },
                                        "x-index": 3
                                    },
                                    "row4": {
                                        "type": "void",
                                        "x-component": "FormGrid",
                                        "x-component-props": {
                                            "maxColumns": 10
                                        },
                                        "name": "row4",
                                        "x-designable-id": "hiead9pu4jz",
                                        "properties": {
                                            "catName": {
                                                "type": "void",
                                                "x-component": "Text",
                                                "x-component-props": {
                                                    "content": "4.地籍及土地利用调查核实",
                                                    "style": {
                                                        "display": "flex",
                                                        "alignItems": "center",
                                                        "justifyContent": "center",
                                                        "height": "100%",
                                                        "fontWeight": "bold",
                                                        "borderRight": "1px solid #d9d9d9",
                                                        "borderBottom": "1px solid #d9d9d9",
                                                        "padding": "10px"
                                                    }
                                                },
                                                "x-decorator-props": {
                                                    "gridSpan": 2
                                                },
                                                "name": "catName",
                                                "x-decorator": "FormGrid.GridColumn",
                                                "x-designable-id": "r09c6k93aqa",
                                                "x-index": 0
                                            },
                                            "catContent": {
                                                "type": "void",
                                                "x-component": "Text",
                                                "x-component-props": {
                                                    "content": "(12) 地籍、不动产登记信息\n(13) 第三次土地利用调查及最新变更调查\n(14) 耕、园、林、草、湿等土地利用情况",
                                                    "style": {
                                                        "whiteSpace": "pre-wrap",
                                                        "padding": "10px",
                                                        "lineHeight": "1.8",
                                                        "borderRight": "1px solid #d9d9d9",
                                                        "borderBottom": "1px solid #d9d9d9"
                                                    }
                                                },
                                                "x-decorator-props": {
                                                    "gridSpan": 6
                                                },
                                                "name": "catContent",
                                                "x-decorator": "FormGrid.GridColumn",
                                                "x-designable-id": "9tcusj35gdh",
                                                "x-index": 1
                                            },
                                            "statusCell": {
                                                "type": "void",
                                                "x-component": "div",
                                                "x-component-props": {
                                                    "style": {
                                                        "display": "flex",
                                                        "alignItems": "center",
                                                        "justifyContent": "center",
                                                        "height": "100%",
                                                        "borderRight": "1px solid #d9d9d9",
                                                        "borderBottom": "1px solid #d9d9d9"
                                                    }
                                                },
                                                "x-decorator-props": {
                                                    "gridSpan": 2
                                                },
                                                "name": "statusCell",
                                                "x-decorator": "FormGrid.GridColumn",
                                                "x-designable-id": "ksxifzxg21c",
                                                "properties": {
                                                    "landUseCheckStatus": {
                                                        "type": "string",
                                                        "x-decorator": "FormItem",
                                                        "x-component": "Radio.Group",
                                                        "x-component-props": {
                                                            "options": [
                                                                {
                                                                    "label": "已核实",
                                                                    "value": "verified"
                                                                },
                                                                {
                                                                    "label": "未核实",
                                                                    "value": "unverified"
                                                                }
                                                            ]
                                                        },
                                                        "name": "landUseCheckStatus",
                                                        "x-decorator-props": {
                                                            "style": {
                                                                "marginBottom": "0px"
                                                            }
                                                        },
                                                        "x-designable-id": "mk686m6jpw0",
                                                        "x-index": 0
                                                    }
                                                },
                                                "x-index": 2
                                            }
                                        },
                                        "x-index": 4
                                    },
                                    "row5": {
                                        "type": "void",
                                        "x-component": "FormGrid",
                                        "x-component-props": {
                                            "maxColumns": 10
                                        },
                                        "name": "row5",
                                        "x-designable-id": "4w66lfqr0oa",
                                        "properties": {
                                            "catName": {
                                                "type": "void",
                                                "x-component": "Text",
                                                "x-component-props": {
                                                    "content": "5.其它",
                                                    "style": {
                                                        "display": "flex",
                                                        "alignItems": "center",
                                                        "justifyContent": "center",
                                                        "height": "100%",
                                                        "fontWeight": "bold",
                                                        "borderRight": "1px solid #d9d9d9",
                                                        "borderBottom": "1px solid #d9d9d9",
                                                        "padding": "10px"
                                                    }
                                                },
                                                "x-decorator-props": {
                                                    "gridSpan": 2
                                                },
                                                "name": "catName",
                                                "x-decorator": "FormGrid.GridColumn",
                                                "x-designable-id": "r9kf9njgo76",
                                                "x-index": 0
                                            },
                                            "otherRemarks": {
                                                "type": "string",
                                                "x-decorator": "FormItem",
                                                "x-decorator-props": {
                                                    "gridSpan": 21,
                                                    "style": {
                                                        "marginBottom": "0px",
                                                        "borderBottom": "1px solid #d9d9d9",
                                                        "borderRight": "1px solid #d9d9d9",
                                                        "padding": "5px"
                                                    }
                                                },
                                                "x-component": "Input.TextArea",
                                                "name": "otherRemarks",
                                                "x-designable-id": "oy9lgdksd25",
                                                "x-validator": [],
                                                "x-component-props": {
                                                    "bordered": true
                                                },
                                                "x-index": 1
                                            }
                                        },
                                        "x-index": 5
                                    }
                                },
                                "x-index": 0
                            }
                        },
                        "x-index": 5
                    },
                    "pmOpinionSection": {
                        "type": "void",
                        "x-component": "Card",
                        "x-component-props": {
                            "title": "项目负责人意见",
                            "size": "small",
                            "styles": {
                                "header": {
                                    "textAlign": "center",
                                    "backgroundColor": "rgb(200, 221, 252)",
                                    "fontSize": "16px",
                                    "fontWeight": "bold",
                                    "border": "1px solid #d9d9d9",
                                    "borderBottom": "none",
                                    "marginTop": "20px"
                                },
                                "body": {
                                    "padding": "16px",
                                    "border": "1px solid #d9d9d9",
                                    "borderTop": "none"
                                }
                            },
                            "style": {
                                "marginTop": "16px"
                            }
                        },
                        "name": "pmOpinionSection",
                        "x-designable-id": "4nce40zv4aw",
                        "properties": {
                            "declarationText": {
                                "type": "void",
                                "x-component": "Text",
                                "x-component-props": {
                                    "content": "声明:经现场踏勘,现场情况已经在表中如实反映,对现场情况基本了解,没有应核实而未核实的内容,重大内容没有疏漏,能够满足规划设计要求,特此评审确认。",
                                    "style": {
                                        "display": "block",
                                        "marginBottom": "10px",
                                        "fontSize": "12px",
                                        "color": "#666"
                                    }
                                },
                                "name": "declarationText",
                                "x-designable-id": "c3tnu5asggm",
                                "x-index": 0
                            },
                            "pmOpinion": {
                                "type": "string",
                                "title": "核实意见",
                                "x-decorator": "FormItem",
                                "x-component": "Input.TextArea",
                                "x-component-props": {
                                    "rows": 4
                                },
                                "name": "pmOpinion",
                                "x-designable-id": "a9k7ijhgllh",
                                "x-index": 1
                            }
                        },
                        "x-index": 6
                    }
                },
                "x-index": 0
            }
        },
        "x-designable-id": "o5fn683n45h"
    }
}